[
  {
    "id": "guanajuato_ley_bebidas_alcoholicas_guanajuato",
    "nombre": "Ley de Bebidas Alcohólicas para el Estado de Guanajuato y sus Municipios",
    "tipo": "Ley",
    "entidad": "guanajuato",
    "url_pdf": "https://congreso-gto.s3.amazonaws.com/uploads/reforma/pdf/3694/LBAEGM_REF_31Diciembre2025.pdf",
    "url_word": "https://congreso-gto.s3.amazonaws.com/uploads/reforma/word/3694/LBAEGM_REF_31Diciembre2025.doc",
    "ultima_reforma": "2025-12-31",
    "estado_vigencia": "vigente",
    "fuente": "",
    "categoria": "leyes"
  },
  {
    "id": "guanajuato_ley_hacienda_guanajuato",
    "nombre": "Ley de Hacienda para el Estado de Guanajuato",
    "tipo": "Ley",
    "entidad": "guanajuato",
    "url_pdf": "https://congreso-gto.s3.amazonaws.com/uploads/reforma/pdf/3692/LHEG_REF_31Diciembre2025.pdf",
    "url_word": "https://congreso-gto.s3.amazonaws.com/uploads/reforma/word/3692/LHEG_REF_31Diciembre2025.doc",
    "ultima_reforma": "2025-12-31",
    "estado_vigencia": "vigente",
    "fuente": "",
    "categoria": "leyes"
  },
  {
    "id": "guanajuato_ley_ingresos_guanajuato_ejercicio_fiscal_2026",
    "nombre": "Ley de Ingresos del Estado de Guanajuato para el Ejercicio Fiscal de 2026",
    "tipo": "Ley",
    "entidad": "guanajuato",
    "url_pdf": "https://congreso-gto.s3.amazonaws.com/uploads/reforma/pdf/3687/LIEG_2026.pdf",
    "url_word": "https://congreso-gto.s3.amazonaws.com/uploads/reforma/word/3687/LIEG_2026.doc",
    "ultima_reforma": "2025-12-30",
    "estado_vigencia": "vigente",
    "fuente": "",
    "categoria": "leyes"
  },
  {
    "id": "guanajuato_ley_coordinacion_fiscal_guanajuato",
    "nombre": "Ley de Coordinación Fiscal del Estado de Guanajuato",
    "tipo": "Ley",
    "entidad": "guanajuato",
    "url_pdf": "https://congreso-gto.s3.amazonaws.com/uploads/reforma/pdf/3690/LCFEG_REF_18Dic2025.pdf",
    "url_word": "https://congreso-gto.s3.amazonaws.com/uploads/reforma/word/3690/LCFEG_REF_18Dic2025.doc",
    "ultima_reforma": "2025-12-18",
    "estado_vigencia": "vigente",
    "fuente": "",
    "categoria": "leyes"
  },
  {
    "id": "guanajuato_ley_presupuesto_general_egresos_guanajuato_ejercicio",
    "nombre": "Ley del Presupuesto General de Egresos del Estado de Guanajuato para el Ejercicio Fiscal de 2026",
    "tipo": "Ley",
    "entidad": "guanajuato",
    "url_pdf": "https://congreso-gto.s3.amazonaws.com/uploads/reforma/pdf/3688/LPGE_2026.pdf",
    "url_word": "https://congreso-gto.s3.amazonaws.com/uploads/reforma/word/3688/LPGE_2026.docx",
    "ultima_reforma": "2025-12-30",
    "estado_vigencia": "vigente",
    "fuente": "",
    "categoria": "leyes"
  },
  {
    "id": "guanajuato_ley_derechos_ninas_ninos_adolescentes_guanajuato",
    "nombre": "Ley de los Derechos de Niñas, Niños y Adolescentes del Estado de Guanajuato",
    "tipo": "Ley",
    "entidad": "guanajuato",
    "url_pdf": "https://congreso-gto.s3.amazonaws.com/uploads/reforma/pdf/3675/LNNAEG_REF_18Diciembre2025.pdf",
    "url_word": "https://congreso-gto.s3.amazonaws.com/uploads/reforma/word/3675/LNNAEG_REF_18Diciembre2025.doc",
    "ultima_reforma": "2025-12-18",
    "estado_vigencia": "vigente",
    "fuente": "",
    "categoria": "leyes"
  },
  {
    "id": "guanajuato_ley_responsabilidades_administrativas_guanajuato",
    "nombre": "Ley de Responsabilidades Administrativas para el Estado de Guanajuato",
    "tipo": "Ley",
    "entidad": "guanajuato",
    "url_pdf": "https://congreso-gto.s3.amazonaws.com/uploads/reforma/pdf/3681/LRAESPEG_REF_11Diciembre2025.pdf",
    "url_word": "https://congreso-gto.s3.amazonaws.com/uploads/reforma/word/3681/LRAESPEG_REF_11Diciembre2025.docx",
    "ultima_reforma": "2025-12-11",
    "estado_vigencia": "vigente",
    "fuente": "",
    "categoria": "leyes"
  },
  {
    "id": "guanajuato_ley_acceso_mujeres_a_vida_libre",
    "nombre": "Ley de Acceso de las Mujeres a una Vida Libre de Violencia Para el Estado de Guanajuato",
    "tipo": "Ley",
    "entidad": "guanajuato",
    "url_pdf": "https://congreso-gto.s3.amazonaws.com/uploads/reforma/pdf/3678/LAMVLVEG_REF_11Diciembre2025.pdf",
    "url_word": "https://congreso-gto.s3.amazonaws.com/uploads/reforma/word/3678/LAMVLVEG_REF_11Diciembre2025.doc",
    "ultima_reforma": "2025-12-11",
    "estado_vigencia": "vigente",
    "fuente": "",
    "categoria": "leyes"
  },
  {
    "id": "guanajuato_ley_desarrollo_competitividad_economica_guanajuato",
    "nombre": "Ley para el Desarrollo y Competitividad Económica del Estado de Guanajuato y sus Municipios",
    "tipo": "Ley",
    "entidad": "guanajuato",
    "url_pdf": "https://congreso-gto.s3.amazonaws.com/uploads/reforma/pdf/3677/LPDCEEG_11Diciembre2025.pdf",
    "url_word": "https://congreso-gto.s3.amazonaws.com/uploads/reforma/word/3677/LPDCEEG_11Diciembre2025.doc",
    "ultima_reforma": "2025-12-11",
    "estado_vigencia": "vigente",
    "fuente": "",
    "categoria": "leyes"
  },
  {
    "id": "guanajuato_ley_movilidad_guanajuato",
    "nombre": "Ley de Movilidad del Estado de Guanajuato y sus Municipios",
    "tipo": "Ley",
    "entidad": "guanajuato",
    "url_pdf": "https://congreso-gto.s3.amazonaws.com/uploads/reforma/pdf/3673/LMEGM_REF_05Dic2025.pdf",
    "url_word": "https://congreso-gto.s3.amazonaws.com/uploads/reforma/word/3673/LMEGM_REF_05Dic2025.docx",
    "ultima_reforma": "2025-12-05",
    "estado_vigencia": "vigente",
    "fuente": "",
    "categoria": "leyes"
  },
  {
    "id": "guanajuato_ley_prevenir_atender_erradicar_discriminacion_guanajuato",
    "nombre": "Ley para Prevenir, Atender y Erradicar la Discriminación en el Estado de Guanajuato.",
    "tipo": "Ley",
    "entidad": "guanajuato",
    "url_pdf": "https://congreso-gto.s3.amazonaws.com/uploads/reforma/pdf/3671/LPAEDEG_REF_03Dic2025.pdf",
    "url_word": "https://congreso-gto.s3.amazonaws.com/uploads/reforma/word/3671/LPAEDEG_REF_03Dic2025.doc",
    "ultima_reforma": "2025-12-03",
    "estado_vigencia": "vigente",
    "fuente": "",
    "categoria": "leyes"
  },
  {
    "id": "guanajuato_ley_salud_guanajuato",
    "nombre": "Ley de Salud del Estado de Guanajuato",
    "tipo": "Ley",
    "entidad": "guanajuato",
    "url_pdf": "https://congreso-gto.s3.amazonaws.com/uploads/reforma/pdf/3667/LSEG_REF_20Noviembre2025.pdf",
    "url_word": "https://congreso-gto.s3.amazonaws.com/uploads/reforma/word/3667/LSEG_REF_20Noviembre2025.doc",
    "ultima_reforma": "2025-11-20",
    "estado_vigencia": "vigente",
    "fuente": "",
    "categoria": "leyes"
  },
  {
    "id": "guanajuato_ley_gobierno_administracion_guanajuato",
    "nombre": "Ley para el Gobierno y Administración de los Municipios del Estado de Guanajuato",
    "tipo": "Ley",
    "entidad": "guanajuato",
    "url_pdf": "https://congreso-gto.s3.amazonaws.com/uploads/reforma/pdf/3666/LGYAMEG_NVA_13Noviembre2025_DL101.pdf",
    "url_word": "https://congreso-gto.s3.amazonaws.com/uploads/reforma/word/3666/LGYAMEG_NVA_13Noviembre2025_DL101.doc",
    "ultima_reforma": "2025-11-13",
    "estado_vigencia": "vigente",
    "fuente": "",
    "categoria": "leyes"
  },
  {
    "id": "guanajuato_ley_fomento_a_actividades_organizaciones_sociedad",
    "nombre": "Ley de Fomento a las Actividades de las Organizaciones de la Sociedad Civil en el Estado de Guanajuato",
    "tipo": "Ley",
    "entidad": "guanajuato",
    "url_pdf": "https://congreso-gto.s3.amazonaws.com/uploads/reforma/pdf/3662/LFAOSC_REF_13Noviembre2025.pdf",
    "url_word": "https://congreso-gto.s3.amazonaws.com/uploads/reforma/word/3662/LFAOSC_REF_13Noviembre2025.doc",
    "ultima_reforma": "2025-11-13",
    "estado_vigencia": "vigente",
    "fuente": "",
    "categoria": "leyes"
  },
  {
    "id": "guanajuato_ley_desarrollo_social_humano_guanajuato",
    "nombre": "Ley de Desarrollo Social y Humano para el Estado y los Municipios de Guanajuato",
    "tipo": "Ley",
    "entidad": "guanajuato",
    "url_pdf": "https://congreso-gto.s3.amazonaws.com/uploads/reforma/pdf/3661/LDSYHEMG_REF_13Noviembre2025.pdf",
    "url_word": "https://congreso-gto.s3.amazonaws.com/uploads/reforma/word/3661/LDSYHEMG_REF_13Noviembre2025.doc",
    "ultima_reforma": "2025-11-13",
    "estado_vigencia": "vigente",
    "fuente": "",
    "categoria": "leyes"
  },
  {
    "id": "guanajuato_ley_proteccion_pueblos_comunidades_indigenas_afromexicanas",
    "nombre": "Ley para la Protección de los Pueblos y Comunidades Indígenas y Afromexicanas en el Estado de Guanajuato",
    "tipo": "Ley",
    "entidad": "guanajuato",
    "url_pdf": "https://congreso-gto.s3.amazonaws.com/uploads/reforma/pdf/3656/LPPYCIEG_REF_30Octubre2025.pdf",
    "url_word": "https://congreso-gto.s3.amazonaws.com/uploads/reforma/word/3656/LPPYCIEG_REF_30Octubre2025.doc",
    "ultima_reforma": "2025-10-30",
    "estado_vigencia": "vigente",
    "fuente": "",
    "categoria": "leyes"
  },
  {
    "id": "guanajuato_ley_fomento_desarrollo_agricola_guanajuato",
    "nombre": "Ley de Fomento y Desarrollo Agrícola para el Estado de Guanajuato",
    "tipo": "Ley",
    "entidad": "guanajuato",
    "url_pdf": "https://congreso-gto.s3.amazonaws.com/uploads/reforma/pdf/3655/LFDAEG_REF_30Octubrel2025.pdf",
    "url_word": "https://congreso-gto.s3.amazonaws.com/uploads/reforma/word/3655/LFDAEG_REF_30Octubrel2025.doc",
    "ultima_reforma": "2025-10-30",
    "estado_vigencia": "vigente",
    "fuente": "",
    "categoria": "leyes"
  },
  {
    "id": "guanajuato_ley_educacion_guanajuato",
    "nombre": "Ley de Educación para el Estado de Guanajuato",
    "tipo": "Ley",
    "entidad": "guanajuato",
    "url_pdf": "https://congreso-gto.s3.amazonaws.com/uploads/reforma/pdf/3654/LEEG_REF_30Octubre2025_DL95.pdf",
    "url_word": "https://congreso-gto.s3.amazonaws.com/uploads/reforma/word/3654/LEEG_REF_30Octubre2025_DL95.docx",
    "ultima_reforma": "2025-10-30",
    "estado_vigencia": "vigente",
    "fuente": "",
    "categoria": "leyes"
  },
  {
    "id": "guanajuato_ley_inclusion_personas_discapacidad_guanajuato",
    "nombre": "Ley de Inclusión para las personas con Discapacidad en el Estado de Guanajuato",
    "tipo": "Ley",
    "entidad": "guanajuato",
    "url_pdf": "https://congreso-gto.s3.amazonaws.com/uploads/reforma/pdf/3651/LDIPDEG_30Octubre_2025.pdf",
    "url_word": "https://congreso-gto.s3.amazonaws.com/uploads/reforma/word/3651/LDIPDEG_30Octubre_2025.doc",
    "ultima_reforma": "2025-10-30",
    "estado_vigencia": "vigente",
    "fuente": "",
    "categoria": "leyes"
  },
  {
    "id": "guanajuato_ley_cultura_fisica_deporte_guanajuato",
    "nombre": "Ley de Cultura Física y Deporte del Estado de Guanajuato",
    "tipo": "Ley",
    "entidad": "guanajuato",
    "url_pdf": "https://congreso-gto.s3.amazonaws.com/uploads/reforma/pdf/3650/LCFYDEG_REF_30Oct2025.pdf",
    "url_word": "https://congreso-gto.s3.amazonaws.com/uploads/reforma/word/3650/LCFYDEG_REF_30Oct2025.doc",
    "ultima_reforma": "2025-10-30",
    "estado_vigencia": "vigente",
    "fuente": "",
    "categoria": "leyes"
  },
  {
    "id": "guanajuato_ley_proteccion_personas_defensoras_derechos_humanos",
    "nombre": "Ley para la Protección de Personas Defensoras de Derechos Humanos y Periodistas del Estado de Guanajuato",
    "tipo": "Ley",
    "entidad": "guanajuato",
    "url_pdf": "https://congreso-gto.s3.amazonaws.com/uploads/reforma/pdf/3649/LPPDDHPEG_14_10_2025.pdf",
    "url_word": "https://congreso-gto.s3.amazonaws.com/uploads/reforma/word/3649/LPPDDHPEG_14_10_2025.docx",
    "ultima_reforma": "2025-10-14",
    "estado_vigencia": "vigente",
    "fuente": "",
    "categoria": "leyes"
  },
  {
    "id": "guanajuato_ley_organica_poder_legislativo_guanajuato",
    "nombre": "Ley Orgánica del Poder Legislativo del Estado de Guanajuato",
    "tipo": "Ley",
    "entidad": "guanajuato",
    "url_pdf": "https://congreso-gto.s3.amazonaws.com/uploads/reforma/pdf/3647/LOPLEG_09102025.pdf",
    "url_word": "https://congreso-gto.s3.amazonaws.com/uploads/reforma/word/3647/LOPLEG_09102025.doc",
    "ultima_reforma": "2025-10-09",
    "estado_vigencia": "vigente",
    "fuente": "",
    "categoria": "leyes"
  },
  {
    "id": "guanajuato_ley_proteccion_atencion_migrante_familias_guanajuato",
    "nombre": "Ley para la Protección y Atención del Migrante y sus Familias del Estado de Guanajuato",
    "tipo": "Ley",
    "entidad": "guanajuato",
    "url_pdf": "https://congreso-gto.s3.amazonaws.com/uploads/reforma/pdf/3643/LPAPMFEG_REF_28Julio2025.pdf",
    "url_word": "https://congreso-gto.s3.amazonaws.com/uploads/reforma/word/3643/LPAPMFEG_REF_28Julio2025.doc",
    "ultima_reforma": "2025-07-28",
    "estado_vigencia": "vigente",
    "fuente": "",
    "categoria": "leyes"
  },
  {
    "id": "guanajuato_ley_juventudes_guanajuato",
    "nombre": "Ley para las Juventudes del Estado de Guanajuato",
    "tipo": "Ley",
    "entidad": "guanajuato",
    "url_pdf": "https://congreso-gto.s3.amazonaws.com/uploads/reforma/pdf/3640/LJEG_REF_28Julio2025.pdf",
    "url_word": "https://congreso-gto.s3.amazonaws.com/uploads/reforma/word/3640/LJEG_REF_28Julio2025.docx",
    "ultima_reforma": "2025-07-28",
    "estado_vigencia": "vigente",
    "fuente": "",
    "categoria": "leyes"
  },
  {
    "id": "guanajuato_ley_derechos_personas_adultas_mayores_guanajuato",
    "nombre": "Ley de los Derechos de las Personas Adultas Mayores para el Estado de Guanajuato",
    "tipo": "Ley",
    "entidad": "guanajuato",
    "url_pdf": "https://congreso-gto.s3.amazonaws.com/uploads/reforma/pdf/3639/LDPAMEG_REF28Julio2025.pdf",
    "url_word": "https://congreso-gto.s3.amazonaws.com/uploads/reforma/word/3639/LDPAMEG_REF28Julio2025.doc",
    "ultima_reforma": "2025-07-28",
    "estado_vigencia": "vigente",
    "fuente": "",
    "categoria": "leyes"
  },
  {
    "id": "guanajuato_ley_patrimonio_inmobiliario_guanajuato",
    "nombre": "Ley del Patrimonio Inmobiliario del Estado de Guanajuato",
    "tipo": "Ley",
    "entidad": "guanajuato",
    "url_pdf": "https://congreso-gto.s3.amazonaws.com/uploads/reforma/pdf/3432/LPIEG_DL14_08Dic2022.pdf",
    "url_word": "https://congreso-gto.s3.amazonaws.com/uploads/reforma/word/3432/LPIEG_DL14_08Dic2022.docx",
    "ultima_reforma": "2022-12-08",
    "estado_vigencia": "vigente",
    "fuente": "",
    "categoria": "leyes"
  },
  {
    "id": "guanajuato_ley_gestion_integral_residuos_guanajuato",
    "nombre": "Ley para la Gestión Integral de Residuos del Estado y los Municipios de Guanajuato",
    "tipo": "Ley",
    "entidad": "guanajuato",
    "url_pdf": "https://congreso-gto.s3.amazonaws.com/uploads/reforma/pdf/3636/LGIREMG_REF_26Junio2025.pdf",
    "url_word": "https://congreso-gto.s3.amazonaws.com/uploads/reforma/word/3636/LGIREMG_REF_26Junio2025.doc",
    "ultima_reforma": "2025-06-26",
    "estado_vigencia": "vigente",
    "fuente": "",
    "categoria": "leyes"
  },
  {
    "id": "guanajuato_ley_prevenir_atender_erradicar_violencia_guanajuato",
    "nombre": "Ley para Prevenir, Atender y Erradicar la Violencia en el Estado de Guanajuato",
    "tipo": "Ley",
    "entidad": "guanajuato",
    "url_pdf": "https://congreso-gto.s3.amazonaws.com/uploads/reforma/pdf/3634/LPAEVEG_REF_25Junio2025.pdf",
    "url_word": "https://congreso-gto.s3.amazonaws.com/uploads/reforma/word/3634/LPAEVEG_REF_25Junio2025.doc",
    "ultima_reforma": "2025-06-25",
    "estado_vigencia": "vigente",
    "fuente": "",
    "categoria": "leyes"
  },
  {
    "id": "guanajuato_ley_victimas_guanajuato",
    "nombre": "Ley de Víctimas del Estado de Guanajuato",
    "tipo": "Ley",
    "entidad": "guanajuato",
    "url_pdf": "https://congreso-gto.s3.amazonaws.com/uploads/reforma/pdf/3630/LVEG_REF_25Junio2025.pdf",
    "url_word": "https://congreso-gto.s3.amazonaws.com/uploads/reforma/word/3630/LVEG_REF_25Junio2025.docx",
    "ultima_reforma": "2025-06-25",
    "estado_vigencia": "vigente",
    "fuente": "",
    "categoria": "leyes"
  },
  {
    "id": "guanajuato_ley_asistencia_social_fortalecimiento_familiar_guanajuato",
    "nombre": "Ley de Asistencia Social y Fortalecimiento Familiar  para el Estado de Guanajuato",
    "tipo": "Ley",
    "entidad": "guanajuato",
    "url_pdf": "https://congreso-gto.s3.amazonaws.com/uploads/reforma/pdf/3626/LASFFEG_REF_25Junio2025.pdf",
    "url_word": "https://congreso-gto.s3.amazonaws.com/uploads/reforma/word/3626/LASFFEG_REF_25Junio2025.doc",
    "ultima_reforma": "2025-06-25",
    "estado_vigencia": "vigente",
    "fuente": "",
    "categoria": "leyes"
  },
  {
    "id": "guanajuato_ley_personas_diversidad_sexual_genero_guanajuato",
    "nombre": "Ley para las Personas de la Diversidad Sexual y de Género del Estado de Guanajuato y sus Municipios",
    "tipo": "Ley",
    "entidad": "guanajuato",
    "url_pdf": "https://congreso-gto.s3.amazonaws.com/uploads/reforma/pdf/3625/LPDSYGEG_REF_25Jun2025.pdf",
    "url_word": "https://congreso-gto.s3.amazonaws.com/uploads/reforma/word/3625/LPDSYGEG_REF_25Jun2025.doc",
    "ultima_reforma": "2025-06-25",
    "estado_vigencia": "vigente",
    "fuente": "",
    "categoria": "leyes"
  },
  {
    "id": "guanajuato_ley_igualdad_entre_mujeres_hombres_guanajuato",
    "nombre": "Ley para la Igualdad entre Mujeres y Hombres del Estado de Guanajuato",
    "tipo": "Ley",
    "entidad": "guanajuato",
    "url_pdf": "https://congreso-gto.s3.amazonaws.com/uploads/reforma/pdf/3624/LIMYHPEG_REF_25Jun2025.pdf",
    "url_word": "https://congreso-gto.s3.amazonaws.com/uploads/reforma/word/3624/LIMYHPEG_REF_25Jun2025.doc",
    "ultima_reforma": "2025-06-25",
    "estado_vigencia": "vigente",
    "fuente": "",
    "categoria": "leyes"
  },
  {
    "id": "guanajuato_ley_prevencion_social_violencia_delincuencia_guanajuato",
    "nombre": "Ley para la Prevención Social de la Violencia y la Delincuencia del Estado de Guanajuato y sus Municipios",
    "tipo": "Ley",
    "entidad": "guanajuato",
    "url_pdf": "https://congreso-gto.s3.amazonaws.com/uploads/reforma/pdf/3623/LPSVDEG_REF_25Jun2025.pdf",
    "url_word": "https://congreso-gto.s3.amazonaws.com/uploads/reforma/word/3623/LPSVDEG_REF_25Jun2025.doc",
    "ultima_reforma": "2025-06-25",
    "estado_vigencia": "vigente",
    "fuente": "",
    "categoria": "leyes"
  },
  {
    "id": "guanajuato_ley_busqueda_personas_desaparecidas_guanajuato",
    "nombre": "Ley para la Búsqueda de Personas Desaparecidas en el Estado de Guanajuato",
    "tipo": "Ley",
    "entidad": "guanajuato",
    "url_pdf": "https://congreso-gto.s3.amazonaws.com/uploads/reforma/pdf/3622/LBPDEG_REF_25Junio2025.pdf",
    "url_word": "https://congreso-gto.s3.amazonaws.com/uploads/reforma/word/3622/LBPDEG_REF_25Junio2025.doc",
    "ultima_reforma": "2025-06-25",
    "estado_vigencia": "vigente",
    "fuente": "",
    "categoria": "leyes"
  },
  {
    "id": "guanajuato_ley_organica_poder_ejecutivo_guanajuato",
    "nombre": "Ley Orgánica del Poder Ejecutivo para el Estado de Guanajuato",
    "tipo": "Ley",
    "entidad": "guanajuato",
    "url_pdf": "https://congreso-gto.s3.amazonaws.com/uploads/reforma/pdf/3620/LOPEEG_REF_25Junio2025.pdf",
    "url_word": "https://congreso-gto.s3.amazonaws.com/uploads/reforma/word/3620/LOPEEG_REF_25Junio2025.doc",
    "ultima_reforma": "2025-06-25",
    "estado_vigencia": "vigente",
    "fuente": "",
    "categoria": "leyes"
  },
  {
    "id": "guanajuato_ley_organica_poder_judicial_guanajuato",
    "nombre": "Ley Orgánica del Poder Judicial del Estado de Guanajuato",
    "tipo": "Ley",
    "entidad": "guanajuato",
    "url_pdf": "https://congreso-gto.s3.amazonaws.com/uploads/reforma/pdf/3614/LOPJEG_REF_28Abril2025.pdf",
    "url_word": "https://congreso-gto.s3.amazonaws.com/uploads/reforma/word/3614/LOPJEG_REF_28Abril2025.docx",
    "ultima_reforma": "2025-04-28",
    "estado_vigencia": "vigente",
    "fuente": "",
    "categoria": "leyes"
  },
  {
    "id": "guanajuato_ley_sistema_seguridad_publica_guanajuato",
    "nombre": "Ley del Sistema de Seguridad Pública del Estado de Guanajuato",
    "tipo": "Ley",
    "entidad": "guanajuato",
    "url_pdf": "https://congreso-gto.s3.amazonaws.com/uploads/reforma/pdf/3611/LSSPEG_DL61_14Marzo2025.pdf",
    "url_word": "https://congreso-gto.s3.amazonaws.com/uploads/reforma/word/3611/LSSPEG_DL61_14Marzo2025.doc",
    "ultima_reforma": "2025-03-14",
    "estado_vigencia": "vigente",
    "fuente": "",
    "categoria": "leyes"
  },
  {
    "id": "guanajuato_ley_ejercicio_control_recursos_publicos_guanajuato",
    "nombre": "Ley para el Ejercicio y Control de los Recursos Públicos para el Estado y los municipios de Guanajuato",
    "tipo": "Ley",
    "entidad": "guanajuato",
    "url_pdf": "https://congreso-gto.s3.amazonaws.com/uploads/reforma/pdf/3602/LEYCRP_REF_27Dic2024.pdf",
    "url_word": "https://congreso-gto.s3.amazonaws.com/uploads/reforma/word/3602/LEYCRP_REF_27Dic2024.doc",
    "ultima_reforma": "2024-12-27",
    "estado_vigencia": "vigente",
    "fuente": "",
    "categoria": "leyes"
  },
  {
    "id": "guanajuato_ley_organica_fiscalia_general_guanajuato",
    "nombre": "Ley Orgánica de la Fiscalía General del Estado de Guanajuato",
    "tipo": "Ley",
    "entidad": "guanajuato",
    "url_pdf": "https://congreso-gto.s3.amazonaws.com/uploads/reforma/pdf/3599/LOFEG_REF_27Dic2024.pdf",
    "url_word": "https://congreso-gto.s3.amazonaws.com/uploads/reforma/word/3599/LOFEG_REF_27Dic2024.docx",
    "ultima_reforma": "2024-12-27",
    "estado_vigencia": "vigente",
    "fuente": "",
    "categoria": "leyes"
  },
  {
    "id": "guanajuato_ley_educacion_superior_guanajuato",
    "nombre": "Ley de Educación Superior para el Estado de Guanajuato",
    "tipo": "Ley",
    "entidad": "guanajuato",
    "url_pdf": "https://congreso-gto.s3.amazonaws.com/uploads/reforma/pdf/3583/LESEG_ORIG_19Julio2024.pdf",
    "url_word": "https://congreso-gto.s3.amazonaws.com/uploads/reforma/word/3583/LESEG_ORIG_19Julio2024.doc",
    "ultima_reforma": "2024-07-19",
    "estado_vigencia": "vigente",
    "fuente": "",
    "categoria": "leyes"
  },
  {
    "id": "guanajuato_ley_derechos_culturales_guanajuato",
    "nombre": "Ley de Derechos Culturales para el Estado de Guanajuato",
    "tipo": "Ley",
    "entidad": "guanajuato",
    "url_pdf": "https://congreso-gto.s3.amazonaws.com/uploads/reforma/pdf/3590/LDCEG_REF_17Sep2024.pdf",
    "url_word": "https://congreso-gto.s3.amazonaws.com/uploads/reforma/word/3590/LDCEG_REF_17Sep2024.doc",
    "ultima_reforma": "2024-09-17",
    "estado_vigencia": "vigente",
    "fuente": "",
    "categoria": "leyes"
  },
  {
    "id": "guanajuato_ley_economia_circular_guanajuato",
    "nombre": "Ley de Economía Circular para el Estado de Guanajuato y sus Municipios",
    "tipo": "Ley",
    "entidad": "guanajuato",
    "url_pdf": "https://congreso-gto.s3.amazonaws.com/uploads/reforma/pdf/3589/LECEG_NVA_17Septiembre2024.pdf",
    "url_word": "https://congreso-gto.s3.amazonaws.com/uploads/reforma/word/3589/LECEG_NVA_17Septiembre2024.doc",
    "ultima_reforma": "2024-09-17",
    "estado_vigencia": "vigente",
    "fuente": "",
    "categoria": "leyes"
  },
  {
    "id": "guanajuato_ley_proteccion_preservacion_ambiente_guanajuato",
    "nombre": "Ley para la Protección y Preservación del Ambiente del Estado de Guanajuato",
    "tipo": "Ley",
    "entidad": "guanajuato",
    "url_pdf": "https://congreso-gto.s3.amazonaws.com/uploads/reforma/pdf/3586/LPPAEG_REF_17Sep2024.pdf",
    "url_word": "https://congreso-gto.s3.amazonaws.com/uploads/reforma/word/3586/LPPAEG_REF_17Sep2024.doc",
    "ultima_reforma": "2024-09-17",
    "estado_vigencia": "vigente",
    "fuente": "",
    "categoria": "leyes"
  },
  {
    "id": "guanajuato_ley_proteccion_animal_guanajuato",
    "nombre": "Ley para la Protección Animal en el Estado de Guanajuato",
    "tipo": "Ley",
    "entidad": "guanajuato",
    "url_pdf": "https://congreso-gto.s3.amazonaws.com/uploads/reforma/pdf/3584/LPAEG_REF_02Agosto2024.pdf",
    "url_word": "https://congreso-gto.s3.amazonaws.com/uploads/reforma/word/3584/LPAEG_REF_02Agosto2024.doc",
    "ultima_reforma": "2024-08-02",
    "estado_vigencia": "vigente",
    "fuente": "",
    "categoria": "leyes"
  },
  {
    "id": "guanajuato_ley_cambio_climatico_guanajuato",
    "nombre": "Ley de Cambio Climático para el Estado de Guanajuato y sus Municipios",
    "tipo": "Ley",
    "entidad": "guanajuato",
    "url_pdf": "https://congreso-gto.s3.amazonaws.com/uploads/reforma/pdf/3573/LCCEGYM_PO_07Jun2024.pdf",
    "url_word": "https://congreso-gto.s3.amazonaws.com/uploads/reforma/word/3573/LCCEGYM_PO_07Jun2024.doc",
    "ultima_reforma": "2024-06-07",
    "estado_vigencia": "vigente",
    "fuente": "",
    "categoria": "leyes"
  },
  {
    "id": "guanajuato_ley_proteccion_derechos_humanos_guanajuato",
    "nombre": "Ley para la Protección de los Derechos Humanos en el Estado de Guanajuato",
    "tipo": "Ley",
    "entidad": "guanajuato",
    "url_pdf": "https://congreso-gto.s3.amazonaws.com/uploads/reforma/pdf/3556/LPDHEG_REF_07Junio2024.pdf",
    "url_word": "https://congreso-gto.s3.amazonaws.com/uploads/reforma/word/3556/LPDHEG_REF_07Junio2024.doc",
    "ultima_reforma": "2024-06-07",
    "estado_vigencia": "vigente",
    "fuente": "",
    "categoria": "leyes"
  },
  {
    "id": "guanajuato_ley_fiscalizacion_superior_guanajuato",
    "nombre": "Ley de Fiscalización Superior del Estado de Guanajuato",
    "tipo": "Ley",
    "entidad": "guanajuato",
    "url_pdf": "https://congreso-gto.s3.amazonaws.com/uploads/reforma/pdf/3546/LFSEG_08Enero2024.pdf",
    "url_word": "https://congreso-gto.s3.amazonaws.com/uploads/reforma/word/3546/LFSEG_08Enero2024.doc",
    "ultima_reforma": "2024-01-08",
    "estado_vigencia": "vigente",
    "fuente": "",
    "categoria": "leyes"
  },
  {
    "id": "guanajuato_ley_seguridad_privada_guanajuato",
    "nombre": "Ley de Seguridad Privada del Estado de Guanajuato",
    "tipo": "Ley",
    "entidad": "guanajuato",
    "url_pdf": "https://congreso-gto.s3.amazonaws.com/uploads/reforma/pdf/3536/LSPEG_REF_21Dic2023.pdf",
    "url_word": "https://congreso-gto.s3.amazonaws.com/uploads/reforma/word/3536/LSPEG_REF_21Dic2023.doc",
    "ultima_reforma": "2023-12-21",
    "estado_vigencia": "vigente",
    "fuente": "",
    "categoria": "leyes"
  },
  {
    "id": "guanajuato_ley_notariado_guanajuato",
    "nombre": "Ley del Notariado para el Estado de Guanajuato",
    "tipo": "Ley",
    "entidad": "guanajuato",
    "url_pdf": "https://congreso-gto.s3.amazonaws.com/uploads/reforma/pdf/3532/LNEG_REF_30Diciembre2022.pdf",
    "url_word": "https://congreso-gto.s3.amazonaws.com/uploads/reforma/word/3532/LNEG_REF_30Diciembre2022.doc",
    "ultima_reforma": "2023-12-13",
    "estado_vigencia": "vigente",
    "fuente": "",
    "categoria": "leyes"
  },
  {
    "id": "guanajuato_ley_organica_tribunal_justicia_administrativa_guanajuato",
    "nombre": "Ley Orgánica del Tribunal de Justicia Administrativa del Estado de Guanajuato",
    "tipo": "Ley",
    "entidad": "guanajuato",
    "url_pdf": "https://congreso-gto.s3.amazonaws.com/uploads/reforma/pdf/3530/LOTJA_REF_13Dic2023.pdf",
    "url_word": "https://congreso-gto.s3.amazonaws.com/uploads/reforma/word/3530/LOTJA_REF_13Dic2023.doc",
    "ultima_reforma": "2023-12-13",
    "estado_vigencia": "vigente",
    "fuente": "",
    "categoria": "leyes"
  },
  {
    "id": "guanajuato_ley_desarrollo_forestal_sustentable_guanajuato",
    "nombre": "Ley de Desarrollo Forestal Sustentable para el Estado y los Municipios de Guanajuato",
    "tipo": "Ley",
    "entidad": "guanajuato",
    "url_pdf": "https://congreso-gto.s3.amazonaws.com/uploads/reforma/pdf/3307/Ley_de_Desarrollo_Forestal_Sustentable_para_el_Estado_y_los_Municipios_de_Guanajuato_PO_23Nov2021.pdf",
    "url_word": "https://congreso-gto.s3.amazonaws.com/uploads/reforma/word/3307/Ley_de_Desarrollo_Forestal_Sustentable_para_el_Estado_y_los_Municipios_de_Guanajuato_PO_23Nov2021.doc",
    "ultima_reforma": "2021-11-23",
    "estado_vigencia": "vigente",
    "fuente": "",
    "categoria": "leyes"
  },
  {
    "id": "guanajuato_ley_archivos_guanajuato",
    "nombre": "Ley de Archivos del Estado de Guanajuato",
    "tipo": "Ley",
    "entidad": "guanajuato",
    "url_pdf": "https://congreso-gto.s3.amazonaws.com/uploads/reforma/pdf/3445/LAEG_REF22Dic2022.pdf",
    "url_word": "https://congreso-gto.s3.amazonaws.com/uploads/reforma/word/3445/LAEG_REF22Dic2022.docx",
    "ultima_reforma": "2022-12-22",
    "estado_vigencia": "vigente",
    "fuente": "",
    "categoria": "leyes"
  },
  {
    "id": "guanajuato_ley_voluntad_anticipada_guanajuato",
    "nombre": "Ley de Voluntad Anticipada para el Estado de Guanajuato",
    "tipo": "Ley",
    "entidad": "guanajuato",
    "url_pdf": "https://congreso-gto.s3.amazonaws.com/uploads/reforma/pdf/1444/LVAEG_03Junio2011.pdf",
    "url_word": "https://congreso-gto.s3.amazonaws.com/uploads/reforma/word/1444/LVAEG_03Junio2011.doc",
    "ultima_reforma": "2011-06-03",
    "estado_vigencia": "vigente",
    "fuente": "",
    "categoria": "leyes"
  },
  {
    "id": "guanajuato_ley_escudo_bandera_himno_guanajuato",
    "nombre": "Ley del Escudo, la Bandera y el Himno del Estado de Guanajuato",
    "tipo": "Ley",
    "entidad": "guanajuato",
    "url_pdf": "https://congreso-gto.s3.amazonaws.com/uploads/reforma/pdf/3529/LEBHEG_NVA_24Nov2023.pdf",
    "url_word": "https://congreso-gto.s3.amazonaws.com/uploads/reforma/word/3529/LEBHEG_NVA_24Nov2023.doc",
    "ultima_reforma": "2023-11-24",
    "estado_vigencia": "vigente",
    "fuente": "",
    "categoria": "leyes"
  },
  {
    "id": "guanajuato_ley_organica_centro_conciliacion_laboral_guanajuato",
    "nombre": "Ley Orgánica del Centro de Conciliación Laboral del Estado de Guanajuato",
    "tipo": "Ley",
    "entidad": "guanajuato",
    "url_pdf": "https://congreso-gto.s3.amazonaws.com/uploads/reforma/pdf/3501/LOCCLEG_DL222_REF_24Oct2023.pdf",
    "url_word": "https://congreso-gto.s3.amazonaws.com/uploads/reforma/word/3501/LOCCLEG_DL222_REF_24Oct2023.docx",
    "ultima_reforma": "2023-10-24",
    "estado_vigencia": "vigente",
    "fuente": "",
    "categoria": "leyes"
  },
  {
    "id": "guanajuato_ley_justicia_civica_guanajuato",
    "nombre": "Ley de Justicia Cívica del Estado de Guanajuato",
    "tipo": "Ley",
    "entidad": "guanajuato",
    "url_pdf": "https://congreso-gto.s3.amazonaws.com/uploads/reforma/pdf/3503/LJCEG_DL_222_REF_24Oct2023.pdf",
    "url_word": "https://congreso-gto.s3.amazonaws.com/uploads/reforma/word/3503/LJCEG_DL_222_REF_24Oct2023.doc",
    "ultima_reforma": "2023-10-24",
    "estado_vigencia": "vigente",
    "fuente": "",
    "categoria": "leyes"
  },
  {
    "id": "guanajuato_ley_trabajo_servidores_publicos_servicio",
    "nombre": "Ley del Trabajo de los Servidores Públicos al Servicio del Estado y de los Municipios",
    "tipo": "Ley",
    "entidad": "guanajuato",
    "url_pdf": "https://congreso-gto.s3.amazonaws.com/uploads/reforma/pdf/3526/LTSPASEYMEG_REF20Nov2023.pdf",
    "url_word": "https://congreso-gto.s3.amazonaws.com/uploads/reforma/word/3526/LTSPASEYMEG_REF20Nov2023.docx",
    "ultima_reforma": "2023-11-20",
    "estado_vigencia": "vigente",
    "fuente": "",
    "categoria": "leyes"
  },
  {
    "id": "guanajuato_ley_instituciones_procedimientos_electorales_guanajuato",
    "nombre": "Ley de Instituciones y Procedimientos Electorales para el Estado de Guanajuato",
    "tipo": "Ley",
    "entidad": "guanajuato",
    "url_pdf": "https://congreso-gto.s3.amazonaws.com/uploads/reforma/pdf/3525/LIPEEG_REF20Nov2023.pdf",
    "url_word": "https://congreso-gto.s3.amazonaws.com/uploads/reforma/word/3525/LIPEEG_REF20Nov2023.doc",
    "ultima_reforma": "2023-11-20",
    "estado_vigencia": "vigente",
    "fuente": "",
    "categoria": "leyes"
  },
  {
    "id": "guanajuato_ley_transparencia_acceso_a_informacion_publica",
    "nombre": "Ley de Transparencia y Acceso a la Información Pública para el Estado de Guanajuato",
    "tipo": "Ley",
    "entidad": "guanajuato",
    "url_pdf": "https://congreso-gto.s3.amazonaws.com/uploads/reforma/pdf/3524/LTAIPEG_REF20Noviembre2023.pdf",
    "url_word": "https://congreso-gto.s3.amazonaws.com/uploads/reforma/word/3524/LTAIPEG_REF20Noviembre2023.docx",
    "ultima_reforma": "2023-11-20",
    "estado_vigencia": "vigente",
    "fuente": "",
    "categoria": "leyes"
  },
  {
    "id": "guanajuato_ley_responsabilidad_patrimonial_guanajuato",
    "nombre": "Ley de Responsabilidad Patrimonial del Estado y los Municipios de Guanajuato",
    "tipo": "Ley",
    "entidad": "guanajuato",
    "url_pdf": "https://congreso-gto.s3.amazonaws.com/uploads/reforma/pdf/3516/LRPEMG_REF20Nov2023.pdf",
    "url_word": "https://congreso-gto.s3.amazonaws.com/uploads/reforma/word/3516/LRPEMG_REF20Nov2023.docx",
    "ultima_reforma": "2023-11-20",
    "estado_vigencia": "vigente",
    "fuente": "",
    "categoria": "leyes"
  },
  {
    "id": "guanajuato_ley_servicio_profesional_carrera_policial_guanajuato",
    "nombre": "Ley del Servicio Profesional de Carrera Policial del Estado y Municipios de Guanajuato",
    "tipo": "Ley",
    "entidad": "guanajuato",
    "url_pdf": "https://congreso-gto.s3.amazonaws.com/uploads/reforma/pdf/3512/LSPCPEMG_DL230_REF_15Nov2023.pdf",
    "url_word": "https://congreso-gto.s3.amazonaws.com/uploads/reforma/word/3512/LSPCPEMG_DL230_REF_15Nov2023.doc",
    "ultima_reforma": "2023-11-15",
    "estado_vigencia": "vigente",
    "fuente": "",
    "categoria": "leyes"
  },
  {
    "id": "guanajuato_ley_convivencia_libre_violencia_entorno_escolar",
    "nombre": "Ley para una Convivencia Libre de Violencia en el Entorno Escolar para el Estado de Guanajuato y sus Municipios",
    "tipo": "Ley",
    "entidad": "guanajuato",
    "url_pdf": "https://congreso-gto.s3.amazonaws.com/uploads/reforma/pdf/3497/LCLVEEEG_DL_225_REF_24Oct2023.pdf",
    "url_word": "https://congreso-gto.s3.amazonaws.com/uploads/reforma/word/3497/LCLVEEEG_DL_225_REF_24Oct2023.doc",
    "ultima_reforma": "2023-10-24",
    "estado_vigencia": "vigente",
    "fuente": "",
    "categoria": "leyes"
  },
  {
    "id": "guanajuato_ley_fomento_a_agricultura_familiar_guanajuato",
    "nombre": "Ley de Fomento a la Agricultura Familiar del Estado de Guanajuato",
    "tipo": "Ley",
    "entidad": "guanajuato",
    "url_pdf": "https://congreso-gto.s3.amazonaws.com/uploads/reforma/pdf/3487/LFAFEG_REF_11Julio2023.pdf",
    "url_word": "https://congreso-gto.s3.amazonaws.com/uploads/reforma/word/3487/LFAFEG_REF_11Julio2023.doc",
    "ultima_reforma": "2023-07-11",
    "estado_vigencia": "vigente",
    "fuente": "",
    "categoria": "leyes"
  },
  {
    "id": "guanajuato_ley_mejora_regulatoria_guanajuato",
    "nombre": "Ley de Mejora Regulatoria para el Estado de Guanajuato",
    "tipo": "Ley",
    "entidad": "guanajuato",
    "url_pdf": "https://congreso-gto.s3.amazonaws.com/uploads/reforma/pdf/3485/LMREG_REF_04Julio2023.pdf",
    "url_word": "https://congreso-gto.s3.amazonaws.com/uploads/reforma/word/3485/LMREG_REF_04Julio2023.doc",
    "ultima_reforma": "2023-07-04",
    "estado_vigencia": "vigente",
    "fuente": "",
    "categoria": "leyes"
  },
  {
    "id": "guanajuato_ley_turismo_guanajuato",
    "nombre": "Ley de Turismo para el Estado de Guanajuato y sus Municipios",
    "tipo": "Ley",
    "entidad": "guanajuato",
    "url_pdf": "https://congreso-gto.s3.amazonaws.com/uploads/reforma/pdf/3455/LTPEGYM_PO_30Dic2022.pdf",
    "url_word": "https://congreso-gto.s3.amazonaws.com/uploads/reforma/word/3455/LTPEGYM_PO_30Dic2022.doc",
    "ultima_reforma": "2022-12-30",
    "estado_vigencia": "vigente",
    "fuente": "",
    "categoria": "leyes"
  },
  {
    "id": "guanajuato_ley_propiedad_condominio_inmuebles_guanajuato",
    "nombre": "Ley de Propiedad en Condominio de Inmuebles para el Estado de Guanajuato",
    "tipo": "Ley",
    "entidad": "guanajuato",
    "url_pdf": "https://congreso-gto.s3.amazonaws.com/uploads/reforma/pdf/3427/LPCIEG_REF_30Nov2022.pdf",
    "url_word": "https://congreso-gto.s3.amazonaws.com/uploads/reforma/word/3427/LPCIEG_REF_30Nov2022.doc",
    "ultima_reforma": "2022-11-30",
    "estado_vigencia": "vigente",
    "fuente": "",
    "categoria": "leyes"
  },
  {
    "id": "guanajuato_ley_obra_publica_servicios_relacionados_misma",
    "nombre": "Ley de Obra Pública y Servicios relacionados con la misma para el Estado y los Municipios de Guanajuato",
    "tipo": "Ley",
    "entidad": "guanajuato",
    "url_pdf": "https://congreso-gto.s3.amazonaws.com/uploads/reforma/pdf/3422/LOPySRLMG_REF_28Octubre2022.pdf",
    "url_word": "https://congreso-gto.s3.amazonaws.com/uploads/reforma/word/3422/LOPySRLMG_REF_28Octubre2022.doc",
    "ultima_reforma": "2022-10-28",
    "estado_vigencia": "vigente",
    "fuente": "",
    "categoria": "leyes"
  },
  {
    "id": "guanajuato_ley_planeacion_guanajuato",
    "nombre": "Ley de Planeación para el Estado de Guanajuato",
    "tipo": "Ley",
    "entidad": "guanajuato",
    "url_pdf": "https://congreso-gto.s3.amazonaws.com/uploads/reforma/pdf/3421/LPEG_REF_28Octubre2022.pdf",
    "url_word": "https://congreso-gto.s3.amazonaws.com/uploads/reforma/word/3421/LPEG_REF_28Octubre2022.doc",
    "ultima_reforma": "2022-10-28",
    "estado_vigencia": "vigente",
    "fuente": "",
    "categoria": "leyes"
  },
  {
    "id": "guanajuato_ley_contrataciones_publicas_guanajuato",
    "nombre": "Ley de Contrataciones Públicas  para el Estado de Guanajuato",
    "tipo": "Ley",
    "entidad": "guanajuato",
    "url_pdf": "https://congreso-gto.s3.amazonaws.com/uploads/reforma/pdf/3412/LCPPEG_REF_21Julio2022.pdf",
    "url_word": "https://congreso-gto.s3.amazonaws.com/uploads/reforma/word/3412/LCPPEG_REF_21Julio2022.doc",
    "ultima_reforma": "2022-07-21",
    "estado_vigencia": "vigente",
    "fuente": "",
    "categoria": "leyes"
  },
  {
    "id": "guanajuato_ley_servicio_administracion_tributaria_guanajuato",
    "nombre": "Ley del Servicio de Administración Tributaria del Estado de Guanajuato",
    "tipo": "Ley",
    "entidad": "guanajuato",
    "url_pdf": "https://congreso-gto.s3.amazonaws.com/uploads/reforma/pdf/3539/LSATEG_REF_30Dic2023.pdf",
    "url_word": "https://congreso-gto.s3.amazonaws.com/uploads/reforma/word/3539/LSATEG_REF_30Dic2023.docx",
    "ultima_reforma": "2023-12-30",
    "estado_vigencia": "vigente",
    "fuente": "",
    "categoria": "leyes"
  },
  {
    "id": "guanajuato_ley_defensoria_publica_penal_guanajuato",
    "nombre": "Ley de la Defensoría Pública Penal del Estado de Guanajuato",
    "tipo": "Ley",
    "entidad": "guanajuato",
    "url_pdf": "https://congreso-gto.s3.amazonaws.com/uploads/reforma/pdf/1382/Ley_de_la_Defensor_a_P_blica_Penal_del_Estado_de_Guanajuato_20141128.pdf",
    "url_word": "https://congreso-gto.s3.amazonaws.com/uploads/reforma/word/1382/Ley_de_la_Defensor_a_P_blica_Penal_del_Estado_de_Guanajuato_20141128.doc",
    "ultima_reforma": "2014-11-28",
    "estado_vigencia": "vigente",
    "fuente": "",
    "categoria": "leyes"
  },
  {
    "id": "guanajuato_ley_aparceria_agricola_ganadera_guanajuato",
    "nombre": "Ley de Aparcería Agrícola y Ganadera del Estado de Guanajuato",
    "tipo": "Ley",
    "entidad": "guanajuato",
    "url_pdf": "https://congreso-gto.s3.amazonaws.com/uploads/reforma/pdf/1297/Ley_de_Aparcer_a_Agr_cola_y_Ganadera_del_Estado_de_Guanajuato_Reforma__07_06_2013.pdf",
    "url_word": "https://congreso-gto.s3.amazonaws.com/uploads/reforma/word/1297/Ley_de_Aparcer_a_Agr_cola_y_Ganadera_del_Estado_de_Guanajuato_Reforma__07_06_2013.doc",
    "ultima_reforma": "2013-06-07",
    "estado_vigencia": "vigente",
    "fuente": "",
    "categoria": "leyes"
  },
  {
    "id": "guanajuato_ley_concesiones_servicios_e_infraestructura_publica",
    "nombre": "Ley de Concesiones de Servicios e Infraestructura Pública para el Estado de Guanajuato",
    "tipo": "Ley",
    "entidad": "guanajuato",
    "url_pdf": "https://congreso-gto.s3.amazonaws.com/uploads/reforma/pdf/1300/20180921.pdf",
    "url_word": "https://congreso-gto.s3.amazonaws.com/uploads/reforma/word/1300/20180921.doc",
    "ultima_reforma": "2018-09-21",
    "estado_vigencia": "vigente",
    "fuente": "",
    "categoria": "leyes"
  },
  {
    "id": "guanajuato_ley_representacion_gratuita_materia_civil",
    "nombre": "Ley de Representación Gratuita en Materia Civil",
    "tipo": "Ley",
    "entidad": "guanajuato",
    "url_pdf": "https://congreso-gto.s3.amazonaws.com/uploads/reforma/pdf/1476/20190801.pdf",
    "url_word": "https://congreso-gto.s3.amazonaws.com/uploads/reforma/word/1476/20190801.doc",
    "ultima_reforma": "2019-08-01",
    "estado_vigencia": "vigente",
    "fuente": "",
    "categoria": "leyes"
  },
  {
    "id": "guanajuato_ley_proteccion_a_abejas_desarrollo_apicola",
    "nombre": "Ley para la Protección a las Abejas y el Desarrollo Apícola para el Estado de Guanajuato",
    "tipo": "Ley",
    "entidad": "guanajuato",
    "url_pdf": "",
    "url_word": "",
    "ultima_reforma": "2019-11-25",
    "estado_vigencia": "vigente",
    "fuente": "",
    "categoria": "leyes"
  },
  {
    "id": "guanajuato_ley_patrimonio_cultural_guanajuato",
    "nombre": "Ley del Patrimonio Cultural del Estado de Guanajuato",
    "tipo": "Ley",
    "entidad": "guanajuato",
    "url_pdf": "https://congreso-gto.s3.amazonaws.com/uploads/reforma/pdf/3178/LEY_DEL_PATRIMONIO_CULTURAL_DEL_ESTADO_DE_GUANAJUATO_PO_19Jul2021_Dto328.pdf",
    "url_word": "https://congreso-gto.s3.amazonaws.com/uploads/reforma/word/3178/LEY_DEL_PATRIMONIO_CULTURAL_DEL_ESTADO_DE_GUANAJUATO_PO_19Jul2021_Dto328.doc",
    "ultima_reforma": "2021-07-19",
    "estado_vigencia": "vigente",
    "fuente": "",
    "categoria": "leyes"
  },
  {
    "id": "guanajuato_ley_declaracion_especial_ausencia_guanjuato",
    "nombre": "Ley de Declaración Especial de Ausencia para el Estado de Guanjuato",
    "tipo": "Ley",
    "entidad": "guanajuato",
    "url_pdf": "https://congreso-gto.s3.amazonaws.com/uploads/reforma/pdf/2753/LDEAEG_22Diciembre2020.pdf",
    "url_word": "https://congreso-gto.s3.amazonaws.com/uploads/reforma/word/2753/LDEAEG_22Diciembre2020.docx",
    "ultima_reforma": "2020-12-22",
    "estado_vigencia": "vigente",
    "fuente": "",
    "categoria": "leyes"
  },
  {
    "id": "guanajuato_ley_fomento_a_actividad_vitivinicola_guanajuato",
    "nombre": "Ley de Fomento a la Actividad Vitivinícola del Estado de Guanajuato",
    "tipo": "Ley",
    "entidad": "guanajuato",
    "url_pdf": "https://congreso-gto.s3.amazonaws.com/uploads/reforma/pdf/1778/LFAVEG_22dic2020.pdf",
    "url_word": "https://congreso-gto.s3.amazonaws.com/uploads/reforma/word/1778/LFAVEG_22dic2020.docx",
    "ultima_reforma": "2020-12-22",
    "estado_vigencia": "vigente",
    "fuente": "",
    "categoria": "leyes"
  },
  {
    "id": "guanajuato_ley_hospedaje_a_traves_plataformas_digitales",
    "nombre": "Ley de Hospedaje a través de Plataformas Digitales del Estado de Guanajuato",
    "tipo": "Ley",
    "entidad": "guanajuato",
    "url_pdf": "https://congreso-gto.s3.amazonaws.com/uploads/reforma/pdf/1774/LHPDEG_09Diciembre2020.pdf",
    "url_word": "https://congreso-gto.s3.amazonaws.com/uploads/reforma/word/1774/LHPDEG_09Diciembre2020.doc",
    "ultima_reforma": "2020-12-09",
    "estado_vigencia": "vigente",
    "fuente": "",
    "categoria": "leyes"
  },
  {
    "id": "guanajuato_ley_proceso_penal_guanajuato",
    "nombre": "Ley del Proceso Penal para el Estado de Guanajuato",
    "tipo": "Ley",
    "entidad": "guanajuato",
    "url_pdf": "https://congreso-gto.s3.amazonaws.com/uploads/reforma/pdf/1466/20160701.pdf",
    "url_word": "https://congreso-gto.s3.amazonaws.com/uploads/reforma/word/1466/20160701.doc",
    "ultima_reforma": "2016-07-01",
    "estado_vigencia": "vigente",
    "fuente": "",
    "categoria": "leyes"
  },
  {
    "id": "guanajuato_ley_proteccion_civil_guanajuato",
    "nombre": "Ley de Protección Civil para el Estado de Guanajuato",
    "tipo": "Ley",
    "entidad": "guanajuato",
    "url_pdf": "https://congreso-gto.s3.amazonaws.com/uploads/reforma/pdf/1431/Ley_de_Protecci_n_Civil_para_el_Estado_de_Guanajuato_20181010.pdf",
    "url_word": "https://congreso-gto.s3.amazonaws.com/uploads/reforma/word/1431/Ley_de_Protecci_n_Civil_para_el_Estado_de_Guanajuato_10_10_2018.doc",
    "ultima_reforma": "2018-10-10",
    "estado_vigencia": "vigente",
    "fuente": "",
    "categoria": "leyes"
  },
  {
    "id": "guanajuato_ley_regularizacion_predios_rusticos_guanajuato",
    "nombre": "Ley para la Regularización de Predios Rústicos en el Estado de Guanajuato",
    "tipo": "Ley",
    "entidad": "guanajuato",
    "url_pdf": "https://congreso-gto.s3.amazonaws.com/uploads/reforma/pdf/3099/Ley_para_la_Regularizaci_n_de_Predios_Rusticos_en_el_Estado_de_Guanajuato_2013_06_07.pdf",
    "url_word": "https://congreso-gto.s3.amazonaws.com/uploads/reforma/word/3099/Ley_para_la_Regularizaci_n_de_Predios_Rusticos_en_el_Estado_de_Guanajuato_2013_06_07.doc",
    "ultima_reforma": "2013-06-07",
    "estado_vigencia": "vigente",
    "fuente": "",
    "categoria": "leyes"
  },
  {
    "id": "guanajuato_ley_proyectos_prestacion_servicios_guanajuato",
    "nombre": "Ley de Proyectos de Prestación de Servicios para el Estado y los Municipios de Guanajuato",
    "tipo": "Ley",
    "entidad": "guanajuato",
    "url_pdf": "https://congreso-gto.s3.amazonaws.com/uploads/reforma/pdf/1435/20161028.pdf",
    "url_word": "https://congreso-gto.s3.amazonaws.com/uploads/reforma/word/1435/20161028.doc",
    "ultima_reforma": "2016-10-28",
    "estado_vigencia": "vigente",
    "fuente": "",
    "categoria": "leyes"
  },
  {
    "id": "guanajuato_ley_profesiones_guanajuato",
    "nombre": "Ley de Profesiones para el Estado de Guanajuato",
    "tipo": "Ley",
    "entidad": "guanajuato",
    "url_pdf": "https://congreso-gto.s3.amazonaws.com/uploads/reforma/pdf/3082/20200722.pdf",
    "url_word": "https://congreso-gto.s3.amazonaws.com/uploads/reforma/word/3082/20200722.doc",
    "ultima_reforma": "2020-07-22",
    "estado_vigencia": "vigente",
    "fuente": "",
    "categoria": "leyes"
  },
  {
    "id": "guanajuato_ley_participacion_ciudadana_guanajuato",
    "nombre": "Ley de Participación Ciudadana para el Estado de Guanajuato",
    "tipo": "Ley",
    "entidad": "guanajuato",
    "url_pdf": "https://congreso-gto.s3.amazonaws.com/uploads/reforma/pdf/3073/20180705.pdf",
    "url_word": "https://congreso-gto.s3.amazonaws.com/uploads/reforma/word/3073/20180705.doc",
    "ultima_reforma": "2018-07-05",
    "estado_vigencia": "vigente",
    "fuente": "",
    "categoria": "leyes"
  },
  {
    "id": "guanajuato_ley_premios_estimulos_merito_ciudadano_guanajuato",
    "nombre": "Ley de Premios y Estímulos al Mérito Ciudadano para el Estado de Guanajuato",
    "tipo": "Ley",
    "entidad": "guanajuato",
    "url_pdf": "https://congreso-gto.s3.amazonaws.com/uploads/reforma/pdf/3070/LPEMC_REF_13Marzo2015.pdf",
    "url_word": "https://congreso-gto.s3.amazonaws.com/uploads/reforma/word/3070/LPEMC_REF_13Marzo2015.doc",
    "ultima_reforma": "2015-03-13",
    "estado_vigencia": "vigente",
    "fuente": "",
    "categoria": "leyes"
  },
  {
    "id": "guanajuato_ley_justicia_alternativa_guanajuato",
    "nombre": "Ley de Justicia Alternativa del Estado de Guanajuato",
    "tipo": "Ley",
    "entidad": "guanajuato",
    "url_pdf": "https://congreso-gto.s3.amazonaws.com/uploads/reforma/pdf/3067/20201230.pdf",
    "url_word": "https://congreso-gto.s3.amazonaws.com/uploads/reforma/word/3067/20201230.doc",
    "ultima_reforma": "2020-12-30",
    "estado_vigencia": "vigente",
    "fuente": "",
    "categoria": "leyes"
  },
  {
    "id": "guanajuato_ley_arancelaria_cobro_honorarios_profesionales_abogados",
    "nombre": "Ley Arancelaria para el Cobro de Honorarios Profesionales de Abogados y Notarios y de Costas Procesales para el Estado de Guanajuato",
    "tipo": "Ley",
    "entidad": "guanajuato",
    "url_pdf": "https://congreso-gto.s3.amazonaws.com/uploads/reforma/pdf/3057/20160701.pdf",
    "url_word": "https://congreso-gto.s3.amazonaws.com/uploads/reforma/word/3057/20160701.docx",
    "ultima_reforma": "2016-07-01",
    "estado_vigencia": "vigente",
    "fuente": "",
    "categoria": "leyes"
  },
  {
    "id": "guanajuato_ley_proteccion_datos_personales_posesion_sujetos",
    "nombre": "Ley de Protección de Datos Personales en Posesión de Sujetos Obligados para el Estado de Guanajuato",
    "tipo": "Ley",
    "entidad": "guanajuato",
    "url_pdf": "https://congreso-gto.s3.amazonaws.com/uploads/reforma/pdf/1643/20171205.pdf",
    "url_word": "https://congreso-gto.s3.amazonaws.com/uploads/reforma/word/1643/20171205.doc",
    "ultima_reforma": "2017-12-05",
    "estado_vigencia": "vigente",
    "fuente": "",
    "categoria": "leyes"
  },
  {
    "id": "guanajuato_ley_seguridad_social_guanajuato",
    "nombre": "Ley de Seguridad Social del Estado de Guanajuato",
    "tipo": "Ley",
    "entidad": "guanajuato",
    "url_pdf": "https://congreso-gto.s3.amazonaws.com/uploads/reforma/pdf/3052/Ley_de_Seguridad_Social.pdf",
    "url_word": "https://congreso-gto.s3.amazonaws.com/uploads/reforma/word/3052/Ley_de_Seguridad_Social.docx",
    "ultima_reforma": "2017-12-20",
    "estado_vigencia": "vigente",
    "fuente": "",
    "categoria": "leyes"
  },
  {
    "id": "guanajuato_ley_sobre_uso_medios_electronicos_firma",
    "nombre": "Ley sobre el uso de medios electrónicos y firma electrónica para el estado de Guanajuato y sus Municipios",
    "tipo": "Ley",
    "entidad": "guanajuato",
    "url_pdf": "https://congreso-gto.s3.amazonaws.com/uploads/reforma/pdf/3093/LSUMEYFEPEG.pdf",
    "url_word": "https://congreso-gto.s3.amazonaws.com/uploads/reforma/word/3093/LSUMEYFEPEG.doc",
    "ultima_reforma": "2020-12-30",
    "estado_vigencia": "vigente",
    "fuente": "",
    "categoria": "leyes"
  },
  {
    "id": "guanajuato_ley_reglamentaria_fraccion_xv_articulo_88",
    "nombre": "Ley Reglamentaria de la Fracción XV del articulo 88 de la Constitución Política del Estado de Guanajuato",
    "tipo": "Ley",
    "entidad": "guanajuato",
    "url_pdf": "https://congreso-gto.s3.amazonaws.com/uploads/reforma/pdf/1570/20180514.pdf",
    "url_word": "https://congreso-gto.s3.amazonaws.com/uploads/reforma/word/1570/20180514.doc",
    "ultima_reforma": "2018-05-14",
    "estado_vigencia": "vigente",
    "fuente": "",
    "categoria": "leyes"
  },
  {
    "id": "guanajuato_ley_regula_a_agentes_inmobiliarios_guanajuato",
    "nombre": "Ley que Regula a los Agentes Inmobiliarios en el Estado de Guanajuato",
    "tipo": "Ley",
    "entidad": "guanajuato",
    "url_pdf": "https://congreso-gto.s3.amazonaws.com/uploads/reforma/pdf/1609/20160701.pdf",
    "url_word": "https://congreso-gto.s3.amazonaws.com/uploads/reforma/word/1609/20160701.doc",
    "ultima_reforma": "2016-07-01",
    "estado_vigencia": "vigente",
    "fuente": "",
    "categoria": "leyes"
  },
  {
    "id": "guanajuato_ley_administracion_disposicion_bienes_relacionados_hechos",
    "nombre": "Ley para la Administración y disposición de bienes relacionados con hechos delictuosos para el estado de Guanajuato",
    "tipo": "Ley",
    "entidad": "guanajuato",
    "url_pdf": "https://congreso-gto.s3.amazonaws.com/uploads/reforma/pdf/1245/20141128.pdf",
    "url_word": "https://congreso-gto.s3.amazonaws.com/uploads/reforma/word/1245/20141128.doc",
    "ultima_reforma": "2014-11-28",
    "estado_vigencia": "vigente",
    "fuente": "",
    "categoria": "leyes"
  },
  {
    "id": "guanajuato_ley_sistema_estatal_anticorrupcion_guanajuato",
    "nombre": "Ley del Sistema Estatal Anticorrupción de Guanajuato",
    "tipo": "Ley",
    "entidad": "guanajuato",
    "url_pdf": "https://congreso-gto.s3.amazonaws.com/uploads/reforma/pdf/1179/20191101.pdf",
    "url_word": "https://congreso-gto.s3.amazonaws.com/uploads/reforma/word/1179/20191101.doc",
    "ultima_reforma": "2019-11-01",
    "estado_vigencia": "vigente",
    "fuente": "",
    "categoria": "leyes"
  },
  {
    "id": "guanajuato_ley_regular_prestacion_servicios_atencion_cuidado",
    "nombre": "Ley para Regular la Prestación de Servicios de Atención, Cuidado y Desarrollo Integral Infantil en el Estado de Guanajuato",
    "tipo": "Ley",
    "entidad": "guanajuato",
    "url_pdf": "https://congreso-gto.s3.amazonaws.com/uploads/reforma/pdf/1638/LEY_PARA_REGULAR_LA_PRESTACI_N_DE_SERVICIOS_DE_ATENCI_N__CUIDADO_Y_DESARROLLO_INTEGRAL_INFANTIL_EN_EL_ESTADO_DE_G.pdf",
    "url_word": "https://congreso-gto.s3.amazonaws.com/uploads/reforma/word/1638/LEY_PARA_REGULAR_LA_PRESTACI_N_DE_SERVICIOS_DE_ATENCI_N__CUIDADO_Y_DESARROLLO_INTEGRAL_INFANTIL_EN_EL_ESTADO_DE_G.doc",
    "ultima_reforma": "2019-08-01",
    "estado_vigencia": "vigente",
    "fuente": "",
    "categoria": "leyes"
  },
  {
    "id": "guanajuato_ley_organica_fuerzas_seguridad_publica",
    "nombre": "Ley Orgánica de las Fuerzas de Seguridad Pública del Estado",
    "tipo": "Ley",
    "entidad": "guanajuato",
    "url_pdf": "https://congreso-gto.s3.amazonaws.com/uploads/reforma/pdf/1477/LFSPEG_REF_15Agosto1995.pdf",
    "url_word": "https://congreso-gto.s3.amazonaws.com/uploads/reforma/word/1477/LFSPEG_REF_15Agosto1995.doc",
    "ultima_reforma": "1995-08-15",
    "estado_vigencia": "vigente",
    "fuente": "",
    "categoria": "leyes"
  },
  {
    "id": "guanajuato_ley_organica_universidad_guanajuato",
    "nombre": "Ley Orgánica de la Universidad de Guanajuato",
    "tipo": "Ley",
    "entidad": "guanajuato",
    "url_pdf": "https://congreso-gto.s3.amazonaws.com/uploads/reforma/pdf/3084/20180720.pdf",
    "url_word": "https://congreso-gto.s3.amazonaws.com/uploads/reforma/word/3084/20180720.doc",
    "ultima_reforma": "2018-07-20",
    "estado_vigencia": "vigente",
    "fuente": "",
    "categoria": "leyes"
  },
  {
    "id": "guanajuato_ley_expropiacion_ocupacion_temporal_limitacion_dominio",
    "nombre": "Ley de Expropiación, de Ocupación Temporal y de Limitación de Dominio para el Estado de Guanajuato",
    "tipo": "Ley",
    "entidad": "guanajuato",
    "url_pdf": "https://congreso-gto.s3.amazonaws.com/uploads/reforma/pdf/1343/20020614.pdf",
    "url_word": "https://congreso-gto.s3.amazonaws.com/uploads/reforma/word/1343/20020614.doc",
    "ultima_reforma": "2002-06-14",
    "estado_vigencia": "vigente",
    "fuente": "",
    "categoria": "leyes"
  },
  {
    "id": "guanajuato_ley_regula_bases_permiso_establecimiento_casas",
    "nombre": "Ley que Regula las Bases del Permiso para el Establecimiento  de las Casas de Empeño en el Estado de Guanajuato y sus Municipios",
    "tipo": "Ley",
    "entidad": "guanajuato",
    "url_pdf": "https://congreso-gto.s3.amazonaws.com/uploads/reforma/pdf/3094/LQRPECEGTO_30Dic2019.pdf",
    "url_word": "https://congreso-gto.s3.amazonaws.com/uploads/reforma/word/3094/LQRPECEGTO_30Dic2019.doc",
    "ultima_reforma": "2019-12-30",
    "estado_vigencia": "vigente",
    "fuente": "",
    "categoria": "leyes"
  },
  {
    "id": "guanajuato_ley_ganadera_guanajuato",
    "nombre": "Ley Ganadera para el Estado de Guanajuato",
    "tipo": "Ley",
    "entidad": "guanajuato",
    "url_pdf": "https://congreso-gto.s3.amazonaws.com/uploads/reforma/pdf/3100/Ley_GanaderaPO_25nov2019.pdf",
    "url_word": "https://congreso-gto.s3.amazonaws.com/uploads/reforma/word/3100/Ley_GanaderaPO_25nov2019.doc",
    "ultima_reforma": "2019-11-25",
    "estado_vigencia": "vigente",
    "fuente": "",
    "categoria": "leyes"
  },
  {
    "id": "guanajuato_ley_ejecucion_medidas_judiciales_sanciones_penales",
    "nombre": "Ley de Ejecución de Medidas Judiciales y Sanciones Penales del Estado de Guanajuato",
    "tipo": "Ley",
    "entidad": "guanajuato",
    "url_pdf": "https://congreso-gto.s3.amazonaws.com/uploads/reforma/pdf/3119/20160701.pdf",
    "url_word": "https://congreso-gto.s3.amazonaws.com/uploads/reforma/word/3119/20160701.doc",
    "ultima_reforma": "2016-07-01",
    "estado_vigencia": "vigente",
    "fuente": "",
    "categoria": "leyes"
  },
  {
    "id": "guanajuato_ley_deuda_publica_guanajuato",
    "nombre": "Ley de Deuda Pública para el Estado y los Municipios de Guanajuato",
    "tipo": "Ley",
    "entidad": "guanajuato",
    "url_pdf": "https://congreso-gto.s3.amazonaws.com/uploads/reforma/pdf/2841/LEY_DE_DEUDA_P_BLICA_PARA_EL_ESTADO_Y_LOS_MUNICIPIOS_DE_GUANAJUATO.pdf",
    "url_word": "https://congreso-gto.s3.amazonaws.com/uploads/reforma/word/2841/LEY_DE_DEUDA_P_BLICA_PARA_EL_ESTADO_Y_LOS_MUNICIPIOS_DE_GUANAJUATO.doc",
    "ultima_reforma": "2016-10-28",
    "estado_vigencia": "vigente",
    "fuente": "",
    "categoria": "leyes"
  },
  {
    "id": "guanajuato_ley_fomento_industria_cinematografica_audiovisual_guanajuato",
    "nombre": "Ley para el Fomento de la Industria Cinematográfica y Audiovisual del Estado de Guanajuato",
    "tipo": "Ley",
    "entidad": "guanajuato",
    "url_pdf": "https://congreso-gto.s3.amazonaws.com/uploads/reforma/pdf/1594/LFICAEG_27Junio_2014.pdf",
    "url_word": "https://congreso-gto.s3.amazonaws.com/uploads/reforma/word/1594/LFICAEG_27Junio_2014.doc",
    "ultima_reforma": "2014-06-27",
    "estado_vigencia": "vigente",
    "fuente": "",
    "categoria": "leyes"
  },
  {
    "id": "guanajuato_ley_prevenir_atender_erradicar_trata_personas",
    "nombre": "Ley para Prevenir, Atender Erradicar la Trata de Personas en el Estado de Guanajuato",
    "tipo": "Ley",
    "entidad": "guanajuato",
    "url_pdf": "https://congreso-gto.s3.amazonaws.com/uploads/reforma/pdf/1590/20140228.pdf",
    "url_word": "https://congreso-gto.s3.amazonaws.com/uploads/reforma/word/1590/20140228.doc",
    "ultima_reforma": "2014-02-28",
    "estado_vigencia": "vigente",
    "fuente": "",
    "categoria": "leyes"
  },
  {
    "id": "guanajuato_ley_secreto_profesional_periodista_guanajuato",
    "nombre": "Ley del Secreto Profesional del Periodista del Estado de Guanajuato",
    "tipo": "Ley",
    "entidad": "guanajuato",
    "url_pdf": "https://congreso-gto.s3.amazonaws.com/uploads/reforma/pdf/1160/20171026.pdf",
    "url_word": "https://congreso-gto.s3.amazonaws.com/uploads/reforma/word/1160/20171026.doc",
    "ultima_reforma": "2017-10-26",
    "estado_vigencia": "vigente",
    "fuente": "",
    "categoria": "leyes"
  },
  {
    "id": "guanajuato_codigo_procedimientos_civiles_guanajuato",
    "nombre": "Código de Procedimientos Civiles para el Estado de Guanajuato",
    "tipo": "Código",
    "entidad": "guanajuato",
    "url_pdf": "https://congreso-gto.s3.amazonaws.com/uploads/reforma/pdf/3004/20190801.pdf",
    "url_word": "https://congreso-gto.s3.amazonaws.com/uploads/reforma/word/3004/20190801.doc",
    "ultima_reforma": "2019-08-01",
    "estado_vigencia": "vigente",
    "fuente": "",
    "categoria": "codigos"
  },
  {
    "id": "guanajuato_codigo_territorial_guanajuato",
    "nombre": "Código Territorial para el Estado y los Municipios de Guanajuato",
    "tipo": "Código",
    "entidad": "guanajuato",
    "url_pdf": "https://congreso-gto.s3.amazonaws.com/uploads/reforma/pdf/3592/CTPEMG_REF_17Sep2024.pdf",
    "url_word": "https://congreso-gto.s3.amazonaws.com/uploads/reforma/word/3592/CTPEMG_REF_17Sep2024.doc",
    "ultima_reforma": "2024-09-17",
    "estado_vigencia": "vigente",
    "fuente": "",
    "categoria": "codigos"
  },
  {
    "id": "guanajuato_codigo_procedimiento_justicia_administrativa_guanajuato",
    "nombre": "Código de Procedimiento y Justicia Administrativa para el Estado y los Municipios de Guanajuato",
    "tipo": "Código",
    "entidad": "guanajuato",
    "url_pdf": "https://congreso-gto.s3.amazonaws.com/uploads/reforma/pdf/3660/CPJAEG_FDE_05Nov2025.pdf",
    "url_word": "https://congreso-gto.s3.amazonaws.com/uploads/reforma/word/3660/CPJAEG_FDE_05Nov2025.doc",
    "ultima_reforma": "2025-11-05",
    "estado_vigencia": "vigente",
    "fuente": "",
    "categoria": "codigos"
  },
  {
    "id": "guanajuato_codigo_penal_guanajuato",
    "nombre": "Código Penal del Estado de Guanajuato",
    "tipo": "Código",
    "entidad": "guanajuato",
    "url_pdf": "https://congreso-gto.s3.amazonaws.com/uploads/reforma/pdf/3695/CPEG_REF_31Diciembre2025.pdf",
    "url_word": "https://congreso-gto.s3.amazonaws.com/uploads/reforma/word/3695/CPEG_REF_31Diciembre2025.doc",
    "ultima_reforma": "2025-12-31",
    "estado_vigencia": "vigente",
    "fuente": "",
    "categoria": "codigos"
  },
  {
    "id": "guanajuato_codigo_civil_guanajuato",
    "nombre": "Código Civil para el Estado de Guanajuato",
    "tipo": "Código",
    "entidad": "guanajuato",
    "url_pdf": "https://congreso-gto.s3.amazonaws.com/uploads/reforma/pdf/3689/CCG_REF_18Diciembre2025_DL113.pdf",
    "url_word": "https://congreso-gto.s3.amazonaws.com/uploads/reforma/word/3689/CCG_REF_18Diciembre2025_DL113.doc",
    "ultima_reforma": "2025-12-18",
    "estado_vigencia": "vigente",
    "fuente": "",
    "categoria": "codigos"
  },
  {
    "id": "guanajuato_codigo_fiscal_guanajuato",
    "nombre": "Código Fiscal para el Estado de Guanajuato",
    "tipo": "Código",
    "entidad": "guanajuato",
    "url_pdf": "https://congreso-gto.s3.amazonaws.com/uploads/reforma/pdf/3693/CFEG_REF_31Diciembre2025.pdf",
    "url_word": "https://congreso-gto.s3.amazonaws.com/uploads/reforma/word/3693/CFEG_REF_31Diciembre2025.docx",
    "ultima_reforma": "2025-12-31",
    "estado_vigencia": "vigente",
    "fuente": "",
    "categoria": "codigos"
  },
  {
    "id": "guanajuato_reglamento_ley_fiscalizacion_superior_guanajuato",
    "nombre": "Reglamento de la Ley de Fiscalización Superior del Estado de Guanajuato",
    "tipo": "Reglamento",
    "entidad": "guanajuato",
    "url_pdf": "https://congreso-gto.s3.amazonaws.com/uploads/reglamento/pdf/5/Reglamento_de_la_Ley_de_Fiscalizacion_D235_PO_216_3ra_Parte_28oct2020.pdf",
    "url_word": "",
    "ultima_reforma": "",
    "estado_vigencia": "vigente",
    "fuente": "",
    "categoria": "reglamentos"
  },
  {
    "id": "guanajuato_reglamento_poder_legislativo_guanajuato_uso_medios",
    "nombre": "Reglamento del Poder Legislativo del Estado de Guanajuato para el uso de Medios Electrónicos y Firma Electrónica.",
    "tipo": "Reglamento",
    "entidad": "guanajuato",
    "url_pdf": "https://congreso-gto.s3.amazonaws.com/uploads/reglamento/pdf/6/REGLAMENTO_DEL_PL_PARA_EL_USO_DE_MEDIOS_ELECTR_NICOS_Y_FIRMA_ELECTR_NICA_PO_02mar2018.pdf",
    "url_word": "",
    "ultima_reforma": "",
    "estado_vigencia": "vigente",
    "fuente": "",
    "categoria": "reglamentos"
  },
  {
    "id": "guanajuato_reglamento_materia_transparencia_acceso_a_informacion",
    "nombre": "Reglamento en Materia de Transparencia y Acceso a la Información Pública del Poder Legislativo del Estado de Guanajuato",
    "tipo": "Reglamento",
    "entidad": "guanajuato",
    "url_pdf": "https://congreso-gto.s3.amazonaws.com/uploads/reglamento/pdf/9/REGLAMENTO_EN_MATERIA_DE_TRANSPARENCIA_FedeE21Abr2017.pdf",
    "url_word": "",
    "ultima_reforma": "",
    "estado_vigencia": "vigente",
    "fuente": "",
    "categoria": "reglamentos"
  },
  {
    "id": "guanajuato_reglamento_contrataciones_publicas_poder_legislativo_guanajuato",
    "nombre": "Reglamento de Contrataciones Públicas del Poder Legislativo del Estado de Guanajuato",
    "tipo": "Reglamento",
    "entidad": "guanajuato",
    "url_pdf": "https://congreso-gto.s3.amazonaws.com/uploads/reglamento/pdf/8/REGLAMENTO_DE_CONTRATACIONES_P_BLICAS_DEL_PODER_LEGISLATIVO.pdf",
    "url_word": "",
    "ultima_reforma": "",
    "estado_vigencia": "vigente",
    "fuente": "",
    "categoria": "reglamentos"
  },
  {
    "id": "guanajuato_reglamento_procedimientos_materia_proteccion_datos_personales",
    "nombre": "Reglamento de los Procedimientos en Materia de Protección de Datos Personales del Poder Legislativo del Estado de Guanajuato.",
    "tipo": "Reglamento",
    "entidad": "guanajuato",
    "url_pdf": "https://congreso-gto.s3.amazonaws.com/uploads/reglamento/pdf/7/REGLAMENTO_DE_LOS_PROCEDIMIENTOS_EN_MATERIA_DE_PROTECCI_N.pdf",
    "url_word": "",
    "ultima_reforma": "",
    "estado_vigencia": "vigente",
    "fuente": "",
    "categoria": "reglamentos"
  },
  {
    "id": "guanajuato_reglamento_archivo_general_poder_legislativo_guanajuato",
    "nombre": "Reglamento del Archivo General del Poder Legislativo del Estado de Guanajuato",
    "tipo": "Reglamento",
    "entidad": "guanajuato",
    "url_pdf": "https://congreso-gto.s3.amazonaws.com/uploads/reglamento/pdf/1/REGLAMENTO_DEL_ARCHIVO_GENERAL_DEL_PODER_LEGISLATIVO.pdf",
    "url_word": "",
    "ultima_reforma": "",
    "estado_vigencia": "vigente",
    "fuente": "",
    "categoria": "reglamentos"
  }
]